youtube_colab_proxy/__init__.py
youtube_colab_proxy/cli.py
youtube_colab_proxy/const.py
youtube_colab_proxy/core.py
youtube_colab_proxy/app/__init__.py
youtube_colab_proxy/app/proxy_app.py
youtube_colab_proxy/app/server.py
youtube_colab_proxy/app/static/app.js
youtube_colab_proxy/app/static/style.css
youtube_colab_proxy/app/templates/index.html
youtube_colab_proxy/integrations/__init__.py
youtube_colab_proxy/integrations/colab.py
youtube_colab_proxy/services/__init__.py
youtube_colab_proxy/services/extractor.py
youtube_colab_proxy/services/resolver.py
youtube_colab_proxy/services/search.py
youtube_colab_proxy/services/streamlink_resolver.py
youtube_colab_proxy/utils/__init__.py
youtube_colab_proxy/utils/input.py
youtube_colab_proxy/utils/security.py
youtube_colab_proxy-1.0.2.dist-info/licenses/LICENSE
youtube_colab_proxy-1.0.2.dist-info/METADATA
youtube_colab_proxy-1.0.2.dist-info/WHEEL
youtube_colab_proxy-1.0.2.dist-info/entry_points.txt
youtube_colab_proxy-1.0.2.dist-info/top_level.txt
youtube_colab_proxy-1.0.2.dist-info/RECORD
