Metadata-Version: 2.4
Name: youtube-colab-proxy
Version: 1.0.2
Summary: A Python web application that provides a YouTube video streaming proxy with a built-in web player. Designed to work seamlessly in Google Colab environments while also supporting local development and deployment.
Author: DAN3002
License:                                  Apache License
Project-URL: Homepage, https://github.com/DAN3002/Youtube-Colab-Proxy
Project-URL: Repository, https://github.com/DAN3002/Youtube-Colab-Proxy
Classifier: Programming Language :: Python :: 3
Classifier: License :: OSI Approved :: Apache Software License
Classifier: Operating System :: OS Independent
Requires-Python: >=3.9
License-File: LICENSE
Requires-Dist: yt-dlp==2025.9.23
Requires-Dist: youtube-search-python
Requires-Dist: flask
Requires-Dist: portpicker
Requires-Dist: streamlink
Dynamic: license-file
